{
  "task_id": "psf__requests-2148",
  "trial_id": 0,
  "stage": "DIFF_EXPORT",
  "error_type": "PRED_READY",
  "signature": "ready_for_harness",
  "context_used": true,
  "context_num_files": 76,
  "repo_context_preview": "Existing files (choose from these):\ntest_requests.py\nsetup.py\ndocs/conf.py\nrequests/api.py\nrequests/auth.py\nrequests/certs.py\nrequests/hooks.py\nrequests/utils.py\nrequests/compat.py\nrequests/models.py\nrequests/cookies.py\nrequests/__init__.py\nrequests/adapters.py\nrequests/sessions.py\nrequests/exceptions.py\nrequests/structures.py\nrequests/status_codes.py\nrequests/packages/__init__.py\nrequests/packages/urllib3/util.py\nrequests/packages/chardet/escsm.py\n... (+56 more)",
  "edit_parse_ok": true,
  "edit_parse_reason": "ok",
  "diff_export_ok": true,
  "diff_export_reason": "ok",
  "edit_script": "{\n  \"edits\": [\n    {\n      \"op\": \"replace_range\",\n      \"path\": \"requests/models.py\",\n      \"start_line\": 694,\n      \"end_line\": 695,\n      \"text\": \"from requests.exceptions import ConnectionError\"\n    },\n    {\n      \"op\": \"replace_range\",\n      \"path\": \"requests/models.py\",\n      \"start_line\": 721,\n      \"end_line\": 722,\n      \"text\": \"if not self.content or self.status_code in requests.codes.connection_errors:\"\n    },\n    {\n      \"op\": \"insert_after\",\n      \"path\": \"requests/models.py\",\n      \"line\": 723,\n      \"text\": \"                raise ConnectionError(response.reason)\"\n    }\n  ]\n}",
  "diff": "diff --git a/requests/models.py b/requests/models.py\nindex 0dc55568..6360bb41 100644\n--- a/requests/models.py\n+++ b/requests/models.py\n@@ -691,9 +691,7 @@ class Response(object):\n     def content(self):\n         \"\"\"Content of the response, in bytes.\"\"\"\n \n-        if self._content is False:\n-            # Read the contents.\n-            try:\n+from requests.exceptions import ConnectionError            try:\n                 if self._content_consumed:\n                     raise RuntimeError(\n                         'The content for this response was already consumed')\n@@ -720,12 +718,10 @@ class Response(object):\n \n         The encoding of the response content is determined based solely on HTTP\n         headers, following RFC 2616 to the letter. If you can take advantage of\n-        non-HTTP knowledge to make a better guess at the encoding, you should\n-        set ``r.encoding`` appropriately before accessing this property.\n-        \"\"\"\n+if not self.content or self.status_code in requests.codes.connection_errors:        \"\"\"\n \n         # Try charset from content-type\n-        content = None\n+                raise ConnectionError(response.reason)        content = None\n         encoding = self.encoding\n \n         if not self.content:\n",
  "stdout": "diff --git a/requests/models.py b/requests/models.py\nindex 0dc55568..6360bb41 100644\n--- a/requests/models.py\n+++ b/requests/models.py\n@@ -691,9 +691,7 @@ class Response(object):\n     def content(self):\n         \"\"\"Content of the response, in bytes.\"\"\"\n \n-        if self._content is False:\n-            # Read the contents.\n-            try:\n+from requests.exceptions import ConnectionError            try:\n                 if self._content_consumed:\n                     raise RuntimeError(\n                         'The content for this response was already consumed')\n@@ -720,12 +718,10 @@ class Response(object):\n \n         The encoding of the response content is determined based solely on HTTP\n         headers, following RFC 2616 to the letter. If you can take advantage of\n-        non-HTTP knowledge to make a better guess at the encoding, you should\n-        set ``r.encoding`` appropriately before accessing this property.\n-        \"\"\"\n+if not self.content or self.status_code in requests.codes.connection_errors:        \"\"\"\n \n         # Try charset from content-type\n-        content = None\n+                raise ConnectionError(response.reason)        content = None\n         encoding = self.encoding\n \n         if not self.content:\n",
  "stderr": ""
}