{
  "task_id": "django__django-14238",
  "trial_id": 0,
  "attempt_index": 0,
  "stage": "EDIT_APPLY",
  "error_type": "APPLY_FAIL",
  "signature": "edit_apply_path_missing",
  "context_used": true,
  "context_num_files": 80,
  "repo_context_preview": "Existing files (choose from these):\ntests/urls.py\ntests/runtests.py\ntests/apps/apps.py\ntests/asgi/urls.py\ntests/i18n/urls.py\ntests/str/tests.py\ntests/wsgi/urls.py\ntests/wsgi/wsgi.py\ndjango/test/html.py\ntests/apps/tests.py\ntests/asgi/tests.py\ntests/i18n/forms.py\ntests/i18n/tests.py\ntests/i18n/utils.py\ntests/mail/tests.py\ntests/str/models.py\ntests/wsgi/tests.py\ndjango/test/utils.py\ntests/apps/models.py\ntests/async/tests.py\n... (+60 more)",
  "edit_parse_ok": true,
  "edit_parse_reason": "ok",
  "diff_export_ok": false,
  "diff_export_reason": "empty_generated_diff:EDIT_APPLY:edit_apply_path_missing",
  "policy_enabled": true,
  "trigger_error_type": "",
  "trigger_signature": "",
  "policy_action": "INITIAL",
  "policy_params": {
    "retry_max_files": 2,
    "context_strategy": "default",
    "prompt_suffix": ""
  },
  "final_selected": false,
  "terminated_by_policy": false,
  "edit_script": "{\n    \"edits\": [\n        {\n            \"op\": \"replace_range\",\n            \"path\": \"example/core/models.py\",\n            \"start_line\": 1,\n            \"end_line\": 1,\n            \"text\": \"from django.db import models\\n\\nclass MyBigAutoField(models.BigAutoField):\\n    pass\\n\\nclass MySmallAutoField(models.SmallAutoField):\\n    pass\\n\\nclass MyModel(models.Model):\\n    id = models.AutoField(primary_key=True)\\n\"\n        }\n    ]\n}",
  "diff": "",
  "stdout": "",
  "stderr": "example/core/models.py"
}