{
  "task_id": "scikit-learn__scikit-learn-14894",
  "trial_id": 0,
  "stage": "DIFF_EXPORT",
  "error_type": "PRED_READY",
  "signature": "ready_for_harness",
  "context_used": true,
  "context_num_files": 80,
  "repo_context_preview": "Existing files (choose from these):\nconftest.py\ndoc/conftest.py\nsklearn/conftest.py\nsklearn/utils/testing.py\nsklearn/tests/__init__.py\nsklearn/tests/test_base.py\nsklearn/tests/test_init.py\nsklearn/tests/test_dummy.py\nsklearn/tests/test_common.py\nsklearn/tests/test_config.py\nsklearn/externals/conftest.py\nsklearn/svm/tests/__init__.py\nsklearn/svm/tests/test_svm.py\nsklearn/tests/test_isotonic.py\nsklearn/tests/test_pipeline.py\nsklearn/tree/tests/__init__.py\nsklearn/cluster/tests/common.py\nsklearn/tree/tests/test_tree.py\nsklearn/utils/tests/__init__.py\nsklearn/impute/tests/__init__.py\n... (+60 more)",
  "edit_parse_ok": true,
  "edit_parse_reason": "ok",
  "diff_export_ok": true,
  "diff_export_reason": "ok",
  "edit_script": "{\n  \"edits\": [\n    {\n      \"op\": \"insert_after\",\n      \"path\": \"sklearn/svm/tests/test_sparse.py\",\n      \"line\": 1,\n      \"text\": \"import numpy as np\\nimport scipy.sparse\\nfrom sklearn.svm import SVR\\n\"\n    },\n    {\n      \"op\": \"insert_after\",\n      \"path\": \"sklearn/svm/tests/test_sparse.py\",\n      \"line\": 2,\n      \"text\": \"def test_empty_support_vectors():\\n    x_train = np.array([[0, 1, 0, 0],\\n                      [0, 0, 0, 1],\\n                      [0, 0, 1, 0],\\n                      [0, 0, 0, 1]])\\n    y_train = np.array([0.04, 0.04, 0.10, 0.16])\\n    model = SVR(C=316.227766017, cache_size=200, coef0=0.0, degree=3, epsilon=0.1,\\n               gamma=1.0, kernel='linear', max_iter=15000,\\n               shrinking=True, tol=0.001, verbose=False)\\n    # dense x_train has no error\\n    model.fit(x_train, y_train)\\n\\n    # convert to sparse\\n    xtrain = scipy.sparse.csr_matrix(x_train)\\n    model.fit(xtrain, y_train)\\n\\n    assert model.support_vectors_.shape == (0, x_train.shape[1]), 'Support vectors should be empty'\\n\"\n    }\n  ]\n}",
  "diff": "diff --git a/sklearn/svm/tests/test_sparse.py b/sklearn/svm/tests/test_sparse.py\nindex 7cf6e8af2a..aa6587743f 100644\n--- a/sklearn/svm/tests/test_sparse.py\n+++ b/sklearn/svm/tests/test_sparse.py\n@@ -1,4 +1,24 @@\n import pytest\n+import numpy as np\n+def test_empty_support_vectors():\n+    x_train = np.array([[0, 1, 0, 0],\n+                      [0, 0, 0, 1],\n+                      [0, 0, 1, 0],\n+                      [0, 0, 0, 1]])\n+    y_train = np.array([0.04, 0.04, 0.10, 0.16])\n+    model = SVR(C=316.227766017, cache_size=200, coef0=0.0, degree=3, epsilon=0.1,\n+               gamma=1.0, kernel='linear', max_iter=15000,\n+               shrinking=True, tol=0.001, verbose=False)\n+    # dense x_train has no error\n+    model.fit(x_train, y_train)\n+\n+    # convert to sparse\n+    xtrain = scipy.sparse.csr_matrix(x_train)\n+    model.fit(xtrain, y_train)\n+\n+    assert model.support_vectors_.shape == (0, x_train.shape[1]), 'Support vectors should be empty'\n+import scipy.sparse\n+from sklearn.svm import SVR\n \n import numpy as np\n from numpy.testing import assert_array_almost_equal, assert_array_equal\n",
  "stdout": "diff --git a/sklearn/svm/tests/test_sparse.py b/sklearn/svm/tests/test_sparse.py\nindex 7cf6e8af2a..aa6587743f 100644\n--- a/sklearn/svm/tests/test_sparse.py\n+++ b/sklearn/svm/tests/test_sparse.py\n@@ -1,4 +1,24 @@\n import pytest\n+import numpy as np\n+def test_empty_support_vectors():\n+    x_train = np.array([[0, 1, 0, 0],\n+                      [0, 0, 0, 1],\n+                      [0, 0, 1, 0],\n+                      [0, 0, 0, 1]])\n+    y_train = np.array([0.04, 0.04, 0.10, 0.16])\n+    model = SVR(C=316.227766017, cache_size=200, coef0=0.0, degree=3, epsilon=0.1,\n+               gamma=1.0, kernel='linear', max_iter=15000,\n+               shrinking=True, tol=0.001, verbose=False)\n+    # dense x_train has no error\n+    model.fit(x_train, y_train)\n+\n+    # convert to sparse\n+    xtrain = scipy.sparse.csr_matrix(x_train)\n+    model.fit(xtrain, y_train)\n+\n+    assert model.support_vectors_.shape == (0, x_train.shape[1]), 'Support vectors should be empty'\n+import scipy.sparse\n+from sklearn.svm import SVR\n \n import numpy as np\n from numpy.testing import assert_array_almost_equal, assert_array_equal\n",
  "stderr": ""
}